setup.py
seo/__init__.py
seo/admin.py
seo/models.py
seo/translation.py
seo/template_context/__init__.py
seo/template_context/context_processors.py
twentytab_seo.egg-info/PKG-INFO
twentytab_seo.egg-info/SOURCES.txt
twentytab_seo.egg-info/dependency_links.txt
twentytab_seo.egg-info/requires.txt
twentytab_seo.egg-info/top_level.txt