Metadata-Version: 1.0
Name: twentytab-seo
Version: 0.1
Summary: A django app that allows to manage the meta contents of pages. He needs twentytab-tree. It also allows to translate information related to pages
Home-page: https://github.com/20tab/twentytab-seo
Author: 20tab S.r.l.
Author-email: info@20tab.com
License: MIT License
Platform: UNKNOWN
